CHANGELOG.md
LICENSE
MANIFEST.in
README.md
VERSION
setup.cfg
setup.py
django_perms.egg-info/PKG-INFO
django_perms.egg-info/SOURCES.txt
django_perms.egg-info/dependency_links.txt
django_perms.egg-info/not-zip-safe
django_perms.egg-info/requires.txt
django_perms.egg-info/top_level.txt
permissions/__init__.py
permissions/exc.py
permissions/meta.py
permissions/registry.py
permissions/templatetags/__init__.py
permissions/templatetags/permissions.py
permissions/tests/__init__.py
permissions/tests/base.py
permissions/tests/test_meta.py
permissions/tests/test_registry.py
permissions/tests/test_templatetags.py
permissions/tests/urls.py