Metadata-Version: 1.1
Name: django-perms
Version: 2.0.0
Summary: Syntactic sugar for handling permission functions in views, templates, and code
Home-page: https://github.com/PSU-OIT-ARC/django-perms
Author: Wyatt Baldwin
Author-email: wbaldwin@pdx.edu
License: UNKNOWN
Platform: UNKNOWN
Classifier: Framework :: Django
Classifier: Programming Language :: Python :: 2
Classifier: Programming Language :: Python :: 2.7
Classifier: Programming Language :: Python :: 3
Classifier: Programming Language :: Python :: 3.3
Classifier: Programming Language :: Python :: 3.4
Classifier: Programming Language :: Python :: 3.5
